threeandthrees
