Metadata-Version: 1.0
Name: threeandthrees
Version: 1.0.2
Summary: A CLI 3&3s game
Home-page: https://github.com/bwarren2/threeandthrees
Author: Ben Warren
Author-email: bwarren2@gmail.com
License: MIT
Platform: any
